{
  "version": "v260331.04 8:48p",
  "release": 4,
  "sha": "d8f982c",
  "fullSha": "d8f982c7760a729a4a340f1d53158b5399efa830",
  "actor": "justinadelacruz",
  "source": "github-main-push",
  "model": "ci",
  "machine": "runnervmrg6be",
  "pushedAt": "2026-03-31T15:47:54-05:00",
  "commits": [{"sha":"1a29cf4","message":"feat: add Ranch House as main rental space with 7 rooms and 10 beds","author":"Justin DeLaCruz"},{"sha":"968a6b4","message":"feat: add min_nights column and show nightly rates on spaces page","author":"Justin DeLaCruz"},{"sha":"d8f982c","message":"feat: add 10-year financial projections page for investors","author":"Justin DeLaCruz"}]
}
